[
      {
            "chef_id": 1,
            "chefPic": "https://nerdyfoodies.com/wp-content/uploads/2020/10/Famous-Chinese-Chefs-1024x683.jpg",
            "chefName": "Julia Child",
            "experienceYears": 50,
            "numRecipes": 5,
            "recipes": [
                  {
                        "recipeName": "Boeuf Bourguignon",
                        "ingredients": [
                              "beef",
                              "bacon",
                              "onions",
                              "carrots",
                              "red wine"
                        ],
                        "recipe_pic": "https://snippetsofparis.com/wp-content/uploads/2020/04/charcuterie-platter-2.jpg",
                        "cookingMethod": "Slow-cooked in a Dutch oven",
                        "rating": 5,
                        "description": "A classic French beef stew, slow-cooked in red wine until tender and flavorful."
                  },
                  {
                        "recipeName": "Coq au Vin",
                        "ingredients": [
                              "chicken",
                              "bacon",
                              "mushrooms",
                              "pearl onions",
                              "red wine"
                        ],
                        "recipe_pic": "https://b1925919.smushcdn.com/1925919/wp-content/uploads/2020/01/french-cheese-board-idea.jpg?lossy=1&strip=1&webp=1",
                        "cookingMethod": "Slow-cooked in a Dutch oven",
                        "rating": 4,
                        "description": "A flavorful chicken dish slow-cooked in red wine with bacon, mushrooms, and pearl onions."
                  },
                  {
                        "recipeName": "Tarte Tatin",
                        "ingredients": [
                              "apples",
                              "sugar",
                              "butter",
                              "puff pastry",
                              "vanilla ice cream"
                        ],
                        "recipe_pic": "https://recipesfromapantry.com/wp-content/uploads/2017/01/How-to-Create-A-French-Charcuterie-Platter-13.jpg",
                        "cookingMethod": "Baked in a skillet",
                        "rating": 5,
                        "description": "A classic French dessert consisting of caramelized apples baked in a skillet with puff pastry on top."
                  }
            ],
            "description": "Julia Child was a legendary French chef, author, and television personality. She is best known for bringing French cuisine to the American public through her cookbook and television show, \"Mastering the Art of French Cooking.\""
      },
      {
            "chef_id": 2,
            "chefPic": "https://cdn.shopify.com/s/files/1/0555/4231/7246/files/about-2_336X.jpg?v=1628774387",
            "chefName": "Julia Child",
            "experienceYears": 50,
            "numRecipes": 5,
            "recipes": [
                  {
                        "recipeName": "Boeuf Bourguignon",
                        "ingredients": [
                              "beef",
                              "bacon",
                              "onions",
                              "carrots",
                              "red wine"
                        ],
                        "recipe_pic": "https://food.fnr.sndimg.com/content/dam/images/food/fullset/2018/6/0/BX1407H_French-Charcuterie-Platter_s4x3.jpg.rend.hgtvcom.616.462.suffix/1523037935589.jpeg",
                        "cookingMethod": "Slow-cooked in a Dutch oven",
                        "rating": 5,
                        "description": "A classic French beef stew, slow-cooked in red wine until tender and flavorful."
                  },
                  {
                        "recipeName": "Coq au Vin",
                        "ingredients": [
                              "chicken",
                              "bacon",
                              "mushrooms",
                              "pearl onions",
                              "red wine"
                        ],
                        "recipe_pic": "https://recipesfromapantry.com/wp-content/uploads/2017/01/How-to-Create-A-French-Charcuterie-Platter-2.jpg",
                        "cookingMethod": "Slow-cooked in a Dutch oven",
                        "rating": 4,
                        "description": "A flavorful chicken dish slow-cooked in red wine with bacon, mushrooms, and pearl onions."
                  },
                  {
                        "recipeName": "Tarte Tatin",
                        "ingredients": [
                              "apples",
                              "sugar",
                              "butter",
                              "puff pastry",
                              "vanilla ice cream"
                        ],
                        "recipe_pic": "https://culinarybutterfly.com/wp-content/uploads/2018/12/Completed-platter.jpg",
                        "cookingMethod": "Baked in a skillet",
                        "rating": 5,
                        "description": "A classic French dessert consisting of caramelized apples baked in a skillet with puff pastry on top."
                  }
            ],
            "description": "Julia Child was a legendary French chef, author, and television personality. She is best known for bringing French cuisine to the American public through her cookbook and television show, \"Mastering the Art of French Cooking.\""
      },
      {
            "chef_id": 3,
            "chefPic": "https://media.hswstatic.com/eyJidWNrZXQiOiJjb250ZW50Lmhzd3N0YXRpYy5jb20iLCJrZXkiOiJnaWZcL3BsYXlcLzMwYWJjNzQ0LWQ3ZmQtNDViYi1hODg1LTI5NjZhNjZiMzgzZC0xMjEwLTY4MC5qcGciLCJlZGl0cyI6eyJyZXNpemUiOnsid2lkdGgiOjgyOH19fQ==",
            "chefName": "Julia Child",
            "experienceYears": 50,
            "numRecipes": 5,
            "recipes": [
                  {
                        "recipeName": "Boeuf Bourguignon",
                        "ingredients": [
                              "beef",
                              "bacon",
                              "onions",
                              "carrots",
                              "red wine"
                        ],
                        "recipe_pic": "https://www.domino.com/uploads/2019/07/22/Simple-Summer-Cheese-Board-1-2.jpg?auto=webp",
                        "cookingMethod": "Slow-cooked in a Dutch oven",
                        "rating": 5,
                        "description": "A classic French beef stew, slow-cooked in red wine until tender and flavorful."
                  },
                  {
                        "recipeName": "Coq au Vin",
                        "ingredients": [
                              "chicken",
                              "bacon",
                              "mushrooms",
                              "pearl onions",
                              "red wine"
                        ],
                        "recipe_pic": "https://foodmatch.com/assets/recipes/20380-4.31.jpg",
                        "cookingMethod": "Slow-cooked in a Dutch oven",
                        "rating": 4,
                        "description": "A flavorful chicken dish slow-cooked in red wine with bacon, mushrooms, and pearl onions."
                  },
                  {
                        "recipeName": "Tarte Tatin",
                        "ingredients": [
                              "apples",
                              "sugar",
                              "butter",
                              "puff pastry",
                              "vanilla ice cream"
                        ],
                        "recipe_pic": "https://chauffeurdrive.com.au/wp-content/uploads/2020/08/Wines.jpg",
                        "rating": 5,
                        "description": "A classic French dessert consisting of caramelized apples baked in a skillet with puff pastry on top."
                  }
            ],
            "description": "Julia Child was a legendary French chef, author, and television personality. She is best known for bringing French cuisine to the American public through her cookbook and television show, \"Mastering the Art of French Cooking.\""
      },
      {
            "chef_id": 4,
            "chefPic": "https://panlasangpinoy.com/wp-content/uploads/2016/05/what-is-a-chef-de-cuisiine.jpg",
            "chefName": "Julia Child",
            "experienceYears": 50,
            "numRecipes": 5,
            "recipes": [
                  {
                        "recipeName": "Boeuf Bourguignon",
                        "ingredients": [
                              "beef",
                              "bacon",
                              "onions",
                              "carrots",
                              "red wine"
                        ],
                        "recipe_pic": "https://images.squarespace-cdn.com/content/v1/5d773a253845a90f7182e473/1637628002071-818GH9Q87PMMQBS7M2HT/M%26M_Shop_KateShanasy_Nov21_lores-1597.jpg",
                        "cookingMethod": "Slow-cooked in a Dutch oven",
                        "rating": 5,
                        "description": "A classic French beef stew, slow-cooked in red wine until tender and flavorful."
                  },
                  {
                        "recipeName": "Coq au Vin",
                        "ingredients": [
                              "chicken",
                              "bacon",
                              "mushrooms",
                              "pearl onions",
                              "red wine"
                        ],
                        "recipe_pic": "https://media.istockphoto.com/id/491618240/photo/cheese-plate.jpg?s=612x612&w=0&k=20&c=DkV2U8LAZa9p164Ac2RojPB4LPzAXYYwvSsjZutWrI4=",
                        "cookingMethod": "Slow-cooked in a Dutch oven",
                        "rating": 4,
                        "description": "A flavorful chicken dish slow-cooked in red wine with bacon, mushrooms, and pearl onions."
                  },
                  {
                        "recipeName": "Tarte Tatin",
                        "ingredients": [
                              "apples",
                              "sugar",
                              "butter",
                              "puff pastry",
                              "vanilla ice cream"
                        ],
                        "recipe_pic": "https://thumbs.dreamstime.com/z/cheese-platter-french-organic-cheeses-figs-nuts-gray-background-top-view-tasty-starter-164823907.jpg",
                        "cookingMethod": "Baked in a skillet",
                        "rating": 5,
                        "description": "A classic French dessert consisting of caramelized apples baked in a skillet with puff pastry on top."
                  }
            ],
            "description": "Julia Child was a legendary French chef, author, and television personality. She is best known for bringing French cuisine to the American public through her cookbook and television show, \"Mastering the Art of French Cooking.\""
      },
      {
            "chef_id": 5,
            "chefPic": "https://i2-prod.nottinghampost.com/incoming/article786799.ece/ALTERNATES/s615b/1_IH161117C-2.jpg",
            "chefName": "Julia Child",
            "experienceYears": 50,
            "numRecipes": 5,
            "recipes": [
                  {
                        "recipeName": "Boeuf Bourguignon",
                        "ingredients": [
                              "beef",
                              "bacon",
                              "onions",
                              "carrots",
                              "red wine"
                        ],
                        "recipe_pic": "https://thumbs.dreamstime.com/z/cheese-platter-french-organic-cheeses-figs-nuts-gray-background-top-view-tasty-starter-164823907.jpg",
                        "cookingMethod": "Slow-cooked in a Dutch oven",
                        "rating": 5,
                        "description": "A classic French beef stew, slow-cooked in red wine until tender and flavorful."
                  },
                  {
                        "recipeName": "Coq au Vin",
                        "ingredients": [
                              "chicken",
                              "bacon",
                              "mushrooms",
                              "pearl onions",
                              "red wine"
                        ],
                        "recipe_pic": "https://images.squarespace-cdn.com/content/v1/5e484ab628c78d6f7e602d73/1606942390121-J5R0EDRMNR9AA80RQVOT/French+Cheese+Board.jpg",
                        "cookingMethod": "Slow-cooked in a Dutch oven",
                        "rating": 4,
                        "description": "A flavorful chicken dish slow-cooked in red wine with bacon, mushrooms, and pearl onions."
                  },
                  {
                        "recipeName": "Tarte Tatin",
                        "ingredients": [
                              "apples",
                              "sugar",
                              "butter",
                              "puff pastry",
                              "vanilla ice cream"
                        ],
                        "recipe_pic": "https://images.squarespace-cdn.com/content/v1/5e484ab628c78d6f7e602d73/1606948814059-72X48I1F4PW0YIQB9AMO/creating+French+cheese+board.JPG",
                        "cookingMethod": "Baked in a skillet",
                        "rating": 5,
                        "description": "A classic French dessert consisting of caramelized apples baked in a skillet with puff pastry on top."
                  }
            ],
            "description": "Julia Child was a legendary French chef, author, and television personality. She is best known for bringing French cuisine to the American public through her cookbook and television show, \"Mastering the Art of French Cooking.\""
      },
      {
            "chef_id": 6,
            "chefPic": "https://assets.simpleviewinc.com/simpleview/image/upload/c_fill,h_560,q_60,w_560/v1/clients/neworleans/square_chef_isaac_toups_new_orleans_top_chefs_a9e893b9-d967-41dc-bf22-c21ab9c2ca0e.jpg",
            "chefName": "Daniel Boulud",
            "experienceYears": 35,
            "numRecipes": 4,
            "recipes": [
                  {
                        "recipeName": "Steak au Poivre",
                        "ingredients": [
                              "beef tenderloin",
                              "cracked black pepper",
                              "heavy cream",
                              "cognac",
                              "butter"
                        ],
                        "recipe_pic": "https://i0.wp.com/thegoodlifefrance.com/wp-content/uploads/2021/04/how-to-make-a-french-cheese-board.jpg?ssl=1",
                        "cookingMethod": "Pan-seared and sautéed with sauce",
                        "rating": 4,
                        "description": "A classic French steak dish coated with cracked black pepper and served with a creamy cognac sauce."
                  },
                  {
                        "recipeName": "Cassoulet",
                        "ingredients": [
                              "white beans",
                              "pork shoulder",
                              "sausage",
                              "duck confit",
                              "breadcrumbs"
                        ],
                        "recipe_pic": "https://cdn.shopify.com/s/files/1/0266/1371/0930/articles/The_perfect_French_Cheeses-1200x900.jpg?v=1571521906",
                        "cookingMethod": "Slow-cooked in a casserole dish",
                        "rating": 5,
                        "description": "A hearty French casserole dish made with white beans, pork shoulder, sausage, and duck confit."
                  },
                  {
                        "recipeName": "Tarte Flambee",
                        "ingredients": [
                              "flour",
                              "water",
                              "salt",
                              "crème fraîche",
                              "bacon"
                        ],
                        "recipe_pic": "https://b1925919.smushcdn.com/1925919/wp-content/uploads/2020/01/french-cheese-board-idea.jpg?lossy=1&strip=1&webp=1",
                        "cookingMethod": "Baked in a wood-fired oven",
                        "rating": 3,
                        "description": "A thin-crust pizza-like dish made with crème fraîche, onions, and bacon, baked in a wood-fired oven."
                  }
            ],
            "description": "Julia Child was a legendary French chef, author, and television personality. She is best known for bringing French cuisine to the American public through her cookbook and television show, \"Mastering the Art of French Cooking.\""
      }
]